python_packaging_at/__init__.py
python_packaging_at/maths.py
python_packaging_att-0.1.1.dist-info/LICENSE
python_packaging_att-0.1.1.dist-info/METADATA
python_packaging_att-0.1.1.dist-info/WHEEL
python_packaging_att-0.1.1.dist-info/top_level.txt
python_packaging_att-0.1.1.dist-info/RECORD
